MANIFEST.in
README.md
conftest.py
requirements.txt
setup.py
tox.ini
djangoevents/__init__.py
djangoevents/app.py
djangoevents/apps.py
djangoevents/domain.py
djangoevents/exceptions.py
djangoevents/models.py
djangoevents/repository.py
djangoevents/schema.py
djangoevents/settings.py
djangoevents/shortcuts.py
djangoevents/unifiedtranscoder.py
djangoevents/utils.py
djangoevents/utils_abstract.py
djangoevents.egg-info/PKG-INFO
djangoevents.egg-info/SOURCES.txt
djangoevents.egg-info/dependency_links.txt
djangoevents.egg-info/not-zip-safe
djangoevents.egg-info/requires.txt
djangoevents.egg-info/top_level.txt
djangoevents/management/__init__.py
djangoevents/management/commands/__init__.py
djangoevents/management/commands/validate_event_schemas.py
djangoevents/migrations/0001_initial.py
djangoevents/migrations/0002_event_event_version.py
djangoevents/migrations/0003_auto_20171220_0404.py
djangoevents/migrations/__init__.py
djangoevents/tests/__init__.py
djangoevents/tests/test_domain.py
djangoevents/tests/test_management.py
djangoevents/tests/test_repo.py
djangoevents/tests/test_schema.py
djangoevents/tests/test_shortcuts.py
djangoevents/tests/test_store.py
djangoevents/tests/test_unifiedtranscoder.py
djangoevents/tests/test_utils.py
djangoevents/tests/test_utils_abstract.py
djangoevents/tests/settings/__init__.py
djangoevents/tests/settings/settings_test.py
djangoevents/tests/settings/settings_test_local.py