Metadata-Version: 1.0
Name: djangoevents
Version: 0.14.1
Summary: Building blocks for building Event Sourcing Django applications.
Home-page: https://github.com/ApplauseOSS/djangoevents
Author: Applause
Author-email: eng@applause.com
License: MIT
Platform: UNKNOWN
